[{"overview":{"complete":"1","score":80,"table":[{"message":"Points Lost","value":-20},{"message":"Final Score","value":80}],"referrer_url":"","created_at":1698245380,"auth":""},"details":[{"title":"Responses:","header":["Question Score","The Question","Your Response","Correct Answer"],"table":[{"data":["Arrange the following sentence, which says \u0022I love black cats\u0022, in the proper order.","8344899f-e641-4426-ba79-07a94dffbfba","[{\u0022value\u0022:\u0022J\u0027\u0022,\u0022legend\u0022:\u0022Pronoun\u0022},{\u0022value\u0022:\u0022aime\u0022,\u0022legend\u0022:\u0022Verb\u0022},{\u0022value\u0022:\u0022les\u0022,\u0022legend\u0022:\u0022Article\u0022},{\u0022value\u0022:\u0022chats\u0022,\u0022legend\u0022:\u0022Noun\u0022},{\u0022value\u0022:\u0022noirs\u0022,\u0022legend\u0022:\u0022Adjective\u0022}]","J\u0027,aime,les,chats,noirs"],"data_style":["question","question_id","response","answer"],"score":100,"feedback":null,"type":"SCORE_QUESTION_ANSWERED","style":"full-value","tag":"div","symbol":"%","graphic":"score","display_score":true},{"data":["Now try arranging the same sentence, but in Spanish.","9900e492-c3d0-4fab-bb3f-11d8658084f4","[{\u0022value\u0022:\u0022Amo\u0022,\u0022legend\u0022:\u0022Verb\u0022},{\u0022value\u0022:\u0022a\u0022,\u0022legend\u0022:\u0022Preposition\u0022},{\u0022value\u0022:\u0022los\u0022,\u0022legend\u0022:\u0022Article\u0022},{\u0022value\u0022:\u0022gatos\u0022,\u0022legend\u0022:\u0022Noun\u0022},{\u0022value\u0022:\u0022negros\u0022,\u0022legend\u0022:\u0022Adjective\u0022}]","Amo,a,los,gatos,negros"],"data_style":["question","question_id","response","answer"],"score":100,"feedback":null,"type":"SCORE_QUESTION_ANSWERED","style":"full-value","tag":"div","symbol":"%","graphic":"score","display_score":true},{"data":["Here is the same sentence again, but in Japanese.","70e58ef8-25cf-4b2f-8f69-10673793ee0b","[{\u0022value\u0022:\u0022Kuroi\u0022,\u0022legend\u0022:\u0022Adjective\u0022},{\u0022value\u0022:\u0022neko\u0022,\u0022legend\u0022:\u0022Noun\u0022},{\u0022value\u0022:\u0022ga\u0022,\u0022legend\u0022:\u0022Preposition\u0022},{\u0022value\u0022:\u0022daisuki\u0022,\u0022legend\u0022:\u0022Verb\u0022}]","Kuroi,neko,ga,daisuki"],"data_style":["question","question_id","response","answer"],"score":100,"feedback":null,"type":"SCORE_QUESTION_ANSWERED","style":"full-value","tag":"div","symbol":"%","graphic":"score","display_score":true},{"data":["The tokens below represent the sentence \u0022I love black cats\u0022 in English. Can you arrange them in the proper order based on their parts of speech?","d1ad7291-f4ed-4d08-a469-7a2542ce94b1","[{\u0022value\u0022:\u0022I\u0022,\u0022legend\u0022:\u0022Pronoun\u0022},{\u0022value\u0022:\u0022love\u0022,\u0022legend\u0022:\u0022Verb\u0022},{\u0022value\u0022:\u0022black\u0022,\u0022legend\u0022:\u0022Adjective\u0022},{\u0022value\u0022:\u0022cats\u0022,\u0022legend\u0022:\u0022Noun\u0022}]","I,love,black,cats"],"data_style":["question","question_id","response","answer"],"score":100,"feedback":null,"type":"SCORE_QUESTION_ANSWERED","style":"full-value","tag":"div","symbol":"%","graphic":"score","display_score":true},{"data":["Finally, try arranging the tokens to say \u0022I love black cats\u0022 in French based on parts of speech. A few extra tokens are included, so be careful!","a8beba94-cf26-40a0-84fa-a10b89218467","[{\u0022value\u0022:\u0022aime\u0022,\u0022legend\u0022:\u0022Verb\u0022},{\u0022value\u0022:\u0022conjunction\u0022,\u0022legend\u0022:\u0022Conjunction\u0022},{\u0022value\u0022:\u0022preposition\u0022,\u0022legend\u0022:\u0022Preposition\u0022},{\u0022value\u0022:\u0022J\u0027\u0022,\u0022legend\u0022:\u0022Pronoun\u0022},{\u0022value\u0022:\u0022les\u0022,\u0022legend\u0022:\u0022Article\u0022},{\u0022value\u0022:\u0022chats\u0022,\u0022legend\u0022:\u0022Noun\u0022},{\u0022value\u0022:\u0022noirs\u0022,\u0022legend\u0022:\u0022Adjective\u0022}]","J\u0027,aime,les,chats,noirs"],"data_style":["question","question_id","response","answer"],"score":0,"feedback":null,"type":"SCORE_QUESTION_ANSWERED","style":"no-value","tag":"div","symbol":"%","graphic":"score","display_score":true}]}]}]