[
	{
		"overview": {
			"complete": "1",
			"score": 45,
			"table": [
				{
					"message": "Points Lost",
					"value": -55
				},
				{
					"message": "Final Score",
					"value": 45
				}
			],
			"referrer_url": "",
			"created_at": "1583512537",
			"auth": ""
		},
		"details": [
			{
				"title": "Responses:",
				"header": [
					"Question Score",
					"The Question",
					"Your Response",
					"Correct Answer"
				],
				"table": [
					{
						"data": [
							"Here's some question text yoooooo",
							"suis,je,poulet,fille",
							"je,suis,poulet,fille"
						],
						"data_style": [
							"question",
							"response",
							"answer"
						],
						"score": 50,
						"feedback": null,
						"type": "SCORE_QUESTION_ANSWERED",
						"style": "partial-value",
						"tag": "div",
						"symbol": "%",
						"graphic": "score",
						"display_score": true
					},
					{
						"data": [
							"For this one, arrange the parts of speech in the expected order.",
							"Pronoun,Article,Adjective,Pronoun,Noun",
							"J',aime,les,chats,noirs"
						],
						"data_style": [
							"question",
							"response",
							"answer"
						],
						"score": 40,
						"feedback": null,
						"type": "SCORE_QUESTION_ANSWERED",
						"style": "partial-value",
						"tag": "div",
						"symbol": "%",
						"graphic": "score",
						"display_score": true
					}
				]
			}
		]
	}
]